LICENSE.txt
MANIFEST.in
README.md
setup.cfg
setup.py
kodrive/__init__.py
kodrive/cli.py
kodrive/cli_syncthing_adapter.py
kodrive/platform_adapter.py
kodrive/syncthing_factory.py
kodrive.egg-info/PKG-INFO
kodrive.egg-info/SOURCES.txt
kodrive.egg-info/dependency_links.txt
kodrive.egg-info/entry_points.txt
kodrive.egg-info/not-zip-safe
kodrive.egg-info/requires.txt
kodrive.egg-info/top_level.txt
kodrive/data/__init__.py
kodrive/data/autostart.py
kodrive/data/config.py
kodrive/data/custom_errors.py
kodrive/data/mac_plist_adt.py
kodrive/data/syncthing_adt.py
kodrive/py_syncthing_adapter/__init__.py
kodrive/utils/__init__.py
kodrive/utils/config_rollbacker.py
kodrive/utils/st_facade_util.py
tests/mock/__init__.py
tests/mock/adapters.py
tests/mock/cli.py