Metadata-Version: 1.1
Name: kodrive
Version: 1.0.19
Summary: Synchronize remote files with local directory.
Home-page: https://github.com/Jvlythical/KodeDrive
Author: Michael Yen
Author-email: lvlichael8@Gmail.Com
License: LICENSE
Platform: any
Classifier: Development Status :: 4 - Beta
Classifier: Environment :: Console
Classifier: Intended Audience :: Developers
Classifier: License :: OSI Approved :: MIT License
Classifier: Operating System :: POSIX
Classifier: Operating System :: MacOS
Classifier: Operating System :: Unix
Classifier: Programming Language :: Python
Classifier: Programming Language :: Python :: 2
Classifier: Topic :: Software Development :: Libraries :: Python Modules
